imagecatalog/__init__.py
imagecatalog/__main__.py
imagecatalog/imagecatalog.py
imagecatalog-0.1.6.dist-info/entry_points.txt
imagecatalog-0.1.6.dist-info/LICENSE
imagecatalog-0.1.6.dist-info/WHEEL
imagecatalog-0.1.6.dist-info/METADATA
imagecatalog-0.1.6.dist-info/RECORD
