Metadata-Version: 2.1
Name: imagecatalog
Version: 0.1.6
Summary: Create a PDF contact sheet from a set of images
License: LICENCE
Keywords: contactsheet
Author: Tim Morello
Author-email: tdmorello@gmail.com
Requires-Python: >=3.7,<4.0
Classifier: Intended Audience :: Developers
Classifier: License :: OSI Approved :: MIT License
Classifier: License :: Other/Proprietary License
Classifier: Operating System :: OS Independent
Classifier: Programming Language :: Python
Classifier: Programming Language :: Python :: 3
Classifier: Programming Language :: Python :: 3 :: Only
Classifier: Programming Language :: Python :: 3.10
Classifier: Programming Language :: Python :: 3.7
Classifier: Programming Language :: Python :: 3.8
Classifier: Programming Language :: Python :: 3.9
Classifier: Topic :: Scientific/Engineering :: Image Processing
Requires-Dist: Pillow (>=9.0.0,<10.0.0)
Requires-Dist: fpdf2 (>=2.4.6,<3.0.0)
Project-URL: Bug Tracker, https://github.com/tdmorello/imagecatalog/issues
Project-URL: Documentation, https://github.com/tdmorello/imagecatalog#README.md
Project-URL: Source Code, https://github.com/tdmorello/imagecatalog
Project-URL: User Support, https://github.com/tdmorello/imagecatalog/issues
